zurich/__init__.py
zurich/exceptions.py
zurich/models.py
zurich/py.typed
zurich/zurich.py
zurich-1.0.1.dist-info/LICENSE
zurich-1.0.1.dist-info/METADATA
zurich-1.0.1.dist-info/WHEEL
zurich-1.0.1.dist-info/RECORD
